magiceight/__init__.py
magiceight/__main__.py
magiceight-1.1.dist-info/LICENSE
magiceight-1.1.dist-info/METADATA
magiceight-1.1.dist-info/WHEEL
magiceight-1.1.dist-info/entry_points.txt
magiceight-1.1.dist-info/top_level.txt
magiceight-1.1.dist-info/RECORD
