Metadata-Version: 2.1
Name: magiceight
Version: 1.1
Summary: A magic eight ball CLI program
Home-page: https://github.com/LordUbuntu/MENACE
Author: Jacobus Burger
Author-email: therealjacoburger@gmail.com
License: MIT
Keywords: python,fortune,magic eight ball,eight ball
Platform: any
Classifier: Development Status :: 5 - Production/Stable
Classifier: Programming Language :: Python :: 3.10
Classifier: Operating System :: OS Independent
Classifier: Topic :: Games/Entertainment
Classifier: Environment :: Console
Classifier: License :: OSI Approved :: MIT License
Requires-Python: >=3.10
License-File: LICENSE
Provides-Extra: dev
Requires-Dist: pytest >=7.2 ; extra == 'dev'
Requires-Dist: twine >=4.0.2 ; extra == 'dev'
Requires-Dist: color50 >=1.0.1 ; extra == 'dev'
